iDeployTest/init.py
iDeployTest/main.py
iDeployTest-1.0.3.dist-info/METADATA
iDeployTest-1.0.3.dist-info/WHEEL
iDeployTest-1.0.3.dist-info/entry_points.txt
iDeployTest-1.0.3.dist-info/top_level.txt
iDeployTest-1.0.3.dist-info/RECORD
