Metadata-Version: 2.1
Name: iDeployTest
Version: 1.0.3
Requires-Dist: Pillow
Requires-Dist: requests
